{".class": "MypyFile", "_fullname": "trade_executor", "is_partial_stub_package": false, "is_stub": false, "names": {".class": "SymbolTable", "CONFIG": {".class": "SymbolTableNode", "cross_ref": "config.CONFIG", "kind": "Gdef"}, "TradeCloser": {".class": "SymbolTableNode", "cross_ref": "trade_closer.TradeCloser", "kind": "Gdef"}, "TradeExecutor": {".class": "SymbolTableNode", "kind": "Gdef", "node": {".class": "TypeInfo", "_promote": null, "abstract_attributes": [], "bases": ["builtins.object"], "declared_metaclass": null, "defn": {".class": "ClassDef", "fullname": "trade_executor.TradeExecutor", "name": "TradeExecutor", "type_vars": []}, "flags": [], "fullname": "trade_executor.TradeExecutor", "metaclass_type": null, "metadata": {}, "module_name": "trade_executor", "mro": ["trade_executor.TradeExecutor", "builtins.object"], "names": {".class": "SymbolTable", "__init__": {".class": "SymbolTableNode", "kind": "Mdef", "node": {".class": "FuncDef", "arg_kinds": [0, 0, 0], "arg_names": ["self", "state", "client"], "flags": [], "fullname": "trade_executor.TradeExecutor.__init__", "name": "__init__", "type": null}}, "client": {".class": "SymbolTableNode", "implicit": true, "kind": "Mdef", "node": {".class": "Var", "flags": [], "fullname": "trade_executor.TradeExecutor.client", "name": "client", "type": {".class": "AnyType", "missing_import_name": null, "source_any": null, "type_of_any": 1}}}, "close": {".class": "SymbolTableNode", "kind": "Mdef", "node": {".class": "FuncDef", "arg_kinds": [0], "arg_names": ["self"], "flags": ["is_coroutine"], "fullname": "trade_executor.TradeExecutor.close", "name": "close", "type": null}}, "cooldown_until": {".class": "SymbolTableNode", "implicit": true, "kind": "Mdef", "node": {".class": "Var", "flags": [], "fullname": "trade_executor.TradeExecutor.cooldown_until", "name": "cooldown_until", "type": {".class": "AnyType", "missing_import_name": null, "source_any": null, "type_of_any": 1}}}, "execute_trade": {".class": "SymbolTableNode", "kind": "Mdef", "node": {".class": "FuncDef", "arg_kinds": [0, 0], "arg_names": ["self", "signal"], "flags": ["is_coroutine"], "fullname": "trade_executor.TradeExecutor.execute_trade", "name": "execute_trade", "type": null}}, "is_cooldown_active": {".class": "SymbolTableNode", "kind": "Mdef", "node": {".class": "FuncDef", "arg_kinds": [0], "arg_names": ["self"], "flags": [], "fullname": "trade_executor.TradeExecutor.is_cooldown_active", "name": "is_cooldown_active", "type": null}}, "monitor_trades": {".class": "SymbolTableNode", "kind": "Mdef", "node": {".class": "FuncDef", "arg_kinds": [0], "arg_names": ["self"], "flags": ["is_coroutine"], "fullname": "trade_executor.TradeExecutor.monitor_trades", "name": "monitor_trades", "type": null}}, "state": {".class": "SymbolTableNode", "implicit": true, "kind": "Mdef", "node": {".class": "Var", "flags": [], "fullname": "trade_executor.TradeExecutor.state", "name": "state", "type": {".class": "AnyType", "missing_import_name": null, "source_any": null, "type_of_any": 1}}}, "trade_closer": {".class": "SymbolTableNode", "implicit": true, "kind": "Mdef", "node": {".class": "Var", "flags": [], "fullname": "trade_executor.TradeExecutor.trade_closer", "name": "trade_closer", "type": {".class": "AnyType", "missing_import_name": null, "source_any": null, "type_of_any": 1}}}}, "tuple_type": null, "type_vars": [], "typeddict_type": null}}, "__doc__": {".class": "SymbolTableNode", "kind": "Gdef", "node": {".class": "Var", "flags": ["is_ready"], "fullname": "trade_executor.__doc__", "name": "__doc__", "type": "builtins.str"}}, "__file__": {".class": "SymbolTableNode", "kind": "Gdef", "node": {".class": "Var", "flags": ["is_ready"], "fullname": "trade_executor.__file__", "name": "__file__", "type": "builtins.str"}}, "__name__": {".class": "SymbolTableNode", "kind": "Gdef", "node": {".class": "Var", "flags": ["is_ready"], "fullname": "trade_executor.__name__", "name": "__name__", "type": "builtins.str"}}, "__package__": {".class": "SymbolTableNode", "kind": "Gdef", "node": {".class": "Var", "flags": ["is_ready"], "fullname": "trade_executor.__package__", "name": "__package__", "type": "builtins.str"}}, "datetime": {".class": "SymbolTableNode", "cross_ref": "datetime.datetime", "kind": "Gdef"}, "logger": {".class": "SymbolTableNode", "kind": "Gdef", "node": {".class": "Var", "flags": [], "fullname": "trade_executor.logger", "name": "logger", "type": "logging.Logger"}}, "logging": {".class": "SymbolTableNode", "cross_ref": "logging", "kind": "Gdef"}, "timedelta": {".class": "SymbolTableNode", "cross_ref": "datetime.timedelta", "kind": "Gdef"}}, "path": "./trade_executor.py"}