{".class": "MypyFile", "_fullname": "telegram._utils.markup", "is_partial_stub_package": false, "is_stub": false, "names": {".class": "SymbolTable", "Sequence": {".class": "SymbolTableNode", "cross_ref": "typing.Sequence", "kind": "Gdef"}, "__doc__": {".class": "SymbolTableNode", "kind": "Gdef", "node": {".class": "Var", "flags": ["is_ready"], "fullname": "telegram._utils.markup.__doc__", "name": "__doc__", "type": "builtins.str"}}, "__file__": {".class": "SymbolTableNode", "kind": "Gdef", "node": {".class": "Var", "flags": ["is_ready"], "fullname": "telegram._utils.markup.__file__", "name": "__file__", "type": "builtins.str"}}, "__name__": {".class": "SymbolTableNode", "kind": "Gdef", "node": {".class": "Var", "flags": ["is_ready"], "fullname": "telegram._utils.markup.__name__", "name": "__name__", "type": "builtins.str"}}, "__package__": {".class": "SymbolTableNode", "kind": "Gdef", "node": {".class": "Var", "flags": ["is_ready"], "fullname": "telegram._utils.markup.__package__", "name": "__package__", "type": "builtins.str"}}, "check_keyboard_type": {".class": "SymbolTableNode", "kind": "Gdef", "node": {".class": "FuncDef", "arg_kinds": [0], "arg_names": ["keyboard"], "flags": [], "fullname": "telegram._utils.markup.check_keyboard_type", "name": "check_keyboard_type", "type": {".class": "CallableType", "arg_kinds": [0], "arg_names": ["keyboard"], "arg_types": ["builtins.object"], "bound_args": [], "def_extras": {"first_arg": null}, "fallback": "builtins.function", "implicit": false, "is_ellipsis_args": false, "name": "check_keyboard_type", "ret_type": "builtins.bool", "variables": []}}}}, "path": "/home/ubuntu/.local/lib/python3.8/site-packages/telegram/_utils/markup.py"}